apicount/__init__.py
apicount/__main__.py
apicount/apicount.py
apicount-0.1.dist-info/LICENSE
apicount-0.1.dist-info/METADATA
apicount-0.1.dist-info/WHEEL
apicount-0.1.dist-info/top_level.txt
apicount-0.1.dist-info/RECORD
