Metadata-Version: 2.1
Name: apicount
Version: 0.1
Summary: Parse api and api groups from sources
Home-page: https://github.com/vadivelmurugank/apicount
Author: Vadivel
Author-email: vadivelmurugank@gmail.com
License: MIT
Platform: UNKNOWN
